{"_":{"V":1},"ContentType":{"Id":"37b25044-29bb-4c78-85e4-7b89f0abaa2c","Name":"ToSic.Eav.DataSources.ContentTypes","Scope":"System.DataSources","Description":"config of content-types","Attributes":[{"Name":"Title","Type":"String","InputType":"string-default","IsTitle":true,"Metadata":[{"Id":42958,"Version":3,"Guid":"0e30efed-8008-417a-b547-3cf9113f08db","Type":{"Name":"@All","Id":"@All"},"Attributes":{"String":{"CustomJavaScript":{"*":""},"DefaultValue":{"*":""},"InputType":{"*":"string-default"},"Name":{"*":"Title / Notes"},"Notes":{"*":"<p>just notes for yourself to better understand what this is for</p>"},"ValidationRegExJavaScript":{"*":""}},"Entity":{"Errors":{"*":[]},"Warnings":{"*":[]}},"Boolean":{"Disabled":{"*":false},"Required":{"*":false},"VisibleInEditUI":{"*":true}}},"Owner":"dnn:userid=1"},{"Id":42962,"Version":2,"Guid":"86e02488-8844-410c-9046-36633463c29e","Type":{"Name":"@string-default","Id":"@string-default"},"Attributes":{"Number":{"RowCount":{"*":3.0}}},"Owner":"dnn:userid=1"}]},{"Name":"AppId","Type":"String","InputType":"string-dropdown-query","IsTitle":false,"Metadata":[{"Id":42960,"Version":5,"Guid":"3c2a0596-9eb5-4c44-8f81-9aa64d90d899","Type":{"Name":"@All","Id":"@All"},"Attributes":{"String":{"CustomJavaScript":{"*":""},"DefaultValue":{"*":""},"InputType":{"*":"string-dropdown-query"},"Name":{"*":"App Id"},"Notes":{"*":"<p>The ID of an app or a token which delivers it. Will use current app if left empty.&nbsp;</p>"},"ValidationRegExJavaScript":{"*":""}},"Entity":{"Errors":{"*":[]},"Warnings":{"*":[]}},"Boolean":{"Disabled":{"*":false},"Required":{"*":false},"VisibleInEditUI":{"*":true}}},"Owner":"dnn:userid=1"},{"Id":42964,"Version":1,"Guid":"be8920b5-02fc-49dd-95b3-a0cb604308f5","Type":{"Name":"@string-default","Id":"@string-default"},"Attributes":{"Number":{"RowCount":{"*":1.0}}},"Owner":"dnn:userid=1"},{"Id":43009,"Version":2,"Guid":"219fe6a9-fde9-45ee-b971-5df7acb2916e","Type":{"Name":"@string-dropdown-query","Id":"@string-dropdown-query"},"Attributes":{"String":{"Label":{"*":"Name"},"Query":{"*":"Eav.Queries.Global.Apps"},"Separator":{"*":","},"StreamName":{"*":"Default"},"UrlParameters":{"*":""},"Value":{"*":"Id"}},"Boolean":{"AllowMultiValue":{"*":false},"EnableTextEntry":{"*":true}}},"Owner":"dnn:userid=1"}]},{"Name":"Scope","Type":"String","InputType":"string-dropdown","IsTitle":false,"Metadata":[{"Id":42961,"Version":3,"Guid":"4aba770d-073d-4dd0-aa6a-de19ac88f701","Type":{"Name":"@All","Id":"@All"},"Attributes":{"String":{"CustomJavaScript":{"*":""},"DefaultValue":{"*":"Default"},"InputType":{"*":"string-dropdown"},"Name":{"*":"Scope"},"Notes":{"*":"<p>The scope for which to get the content-types - by default it's always Default</p>"},"ValidationRegExJavaScript":{"*":""}},"Entity":{"Errors":{"*":[]},"Warnings":{"*":[]}},"Boolean":{"Disabled":{"*":false},"Required":{"*":false},"VisibleInEditUI":{"*":true}}},"Owner":"dnn:userid=1"},{"Id":42965,"Version":1,"Guid":"4d4ea6d4-c7e4-4ab1-aae4-ecaabf25bd8c","Type":{"Name":"@string-dropdown","Id":"@string-dropdown"},"Attributes":{"String":{"DropdownValues":{"*":"Default"}},"Boolean":{"EnableTextEntry":{"*":true}}},"Owner":"dnn:userid=1"}]}],"Metadata":[{"Id":43010,"Version":2,"Guid":"6906e6b4-35df-4c2d-8884-9cc0c520ffc4","Type":{"Name":"ContentType","Id":"ContentType"},"Attributes":{"String":{"Description":{"*":"config of content-types"},"EditInstructions":{"*":"<p>Query what content-types you want. If left blank, will use current app. Read more about this in the <a href=\"https://docs.2sxc.org/api/dot-net/ToSic.Eav.DataSources.System.ContentTypes.html\" target=\"_blank\" rel=\"noopener\">wiki</a>.</p>"},"Label":{"*":"System - Get ContentTypes"},"ListInstructions":{"*":""},"Notes":{"*":""}},"Hyperlink":{"Icon":{"*":""},"Link":{"*":""}}},"Owner":"dnn:userid=1","For":{"Target":"ContentType","String":"37b25044-29bb-4c78-85e4-7b89f0abaa2c"}}]}}