{"_":{"V":1},"Entity":{"Id":144505,"Version":2,"Guid":"3e6811a8-87ab-4954-8402-6e2b3d80c6e2","Type":{"Name":"⚙️WebResource","Id":"66f19c62-371e-4ad1-a98b-de0745507be4"},"Attributes":{"String":{"Html":{"en-us":"<script defer async data-enableoptimizations=\"bottom\" src=\"https://cdnjs.cloudflare.com/ajax/libs/font-awesome/6.1.1/js/all.min.js\" integrity=\"sha512-6PM0qYu5KExuNcKt5bURAoT6KCThUmHRewN3zUFNaoI6Di7XJPTMoT6K0nsagZKk2OB4L7E3q1uQKHNHd4stIQ==\" crossorigin=\"anonymous\" referrerpolicy=\"no-referrer\"></script>"},"ItemIdentifier":{"en-us":"FontAwesome6"},"SettingsIdentifier":{"en-us":"WebResources.FontAwesome6"}},"Boolean":{"Enabled":{"en-us":true}}},"Owner":"dnn:userid=41","Metadata":[{"Id":144506,"Version":1,"Guid":"be43a43e-56c9-4660-97a4-a3aadafa370e","Type":{"Name":"NoteDecorator","Id":"5e958dc6-2922-4d68-835c-7b9711538b12"},"Attributes":{"String":{"Note":{"en-us":"<p>Get updated links from the <a href=\"https://cdnjs.com/libraries/font-awesome/6.1.1\" target=\"_blank\" rel=\"noopener\">CDNJS</a>.</p>"},"NoteType":{"en-us":"note"},"Title":{"en-us":"Get updated links from the CDN..."}}},"Owner":"dnn:userid=41","For":{"Target":"Entity","TargetType":4,"Guid":"3e6811a8-87ab-4954-8402-6e2b3d80c6e2"}}]}}