{"_":{"V":1},"ContentType":{"Id":"8443e1fa-b821-49ed-8177-08ed9474fd7b","Name":"Recipes","Scope":"2SexyContent","Description":"","Attributes":[{"Name":"Name","Type":"String","IsTitle":true,"Metadata":[{"Id":46103,"Version":2,"Guid":"dbaec325-099e-4bfe-8d78-2b03a168b4ec","Type":{"Name":"@All","Id":"@All"},"Attributes":{"String":{"CustomJavaScript":{"*":""},"DefaultValue":{"*":""},"InputType":{"*":"string-default"},"Name":{"*":"Name"},"Notes":{"*":"name of this recipe"},"ValidationRegExJavaScript":{"*":""}},"Boolean":{"Disabled":{"*":false},"Required":{"*":false},"VisibleInEditUI":{"*":true}}}},{"Id":46132,"Version":1,"Guid":"6db92769-b3a4-4fc2-8d0d-5b3fbb7b84f1","Type":{"Name":"@String","Id":"@String"},"Attributes":{"String":{"DropdownValues":{"*":""},"InputType":{"*":""},"ValidationAutomatic":{"*":""},"ValidationRegEx":{"*":""},"ValidationRegExJavaScript":{"*":""}},"Number":{"RowCount":{"*":1.0}}},"Owner":"dnn:userid=1"},{"Id":46133,"Version":1,"Guid":"f33f6756-0791-4cf8-8055-e2e2c7c46841","Type":{"Name":"@string-default","Id":"@string-default"},"Attributes":{}}]},{"Name":"Library","Type":"Entity","IsTitle":false,"Metadata":[{"Id":46104,"Version":2,"Guid":"dc073acf-d89b-46c4-ab3a-511a1e428ed2","Type":{"Name":"@All","Id":"@All"},"Attributes":{"String":{"CustomJavaScript":{"*":""},"DefaultValue":{"*":""},"InputType":{"*":"entity-default"},"Name":{"*":"Library"},"Notes":{"*":"what library this recipe is in"},"ValidationRegExJavaScript":{"*":""}},"Boolean":{"Disabled":{"*":false},"Required":{"*":true},"VisibleInEditUI":{"*":true}}}},{"Id":46105,"Version":2,"Guid":"fedbb1a1-f908-4010-b083-551e15ea355b","Type":{"Name":"@Entity","Id":"@Entity"},"Attributes":{"String":{"EntityType":{"*":"Libraries"}},"Boolean":{"AllowMultiValue":{"*":false},"EnableAddExisting":{"*":true},"EnableCreate":{"*":true},"EnableDelete":{"*":false},"EnableEdit":{"*":false},"EnableRemove":{"*":true}}}}]},{"Name":"Recipe","Type":"String","IsTitle":false,"Metadata":[{"Id":46106,"Version":2,"Guid":"0c834e89-47f2-4ab7-a484-b78f170c6242","Type":{"Name":"@All","Id":"@All"},"Attributes":{"String":{"CustomJavaScript":{"*":""},"DefaultValue":{"*":""},"InputType":{"*":"string-wysiwyg"},"Name":{"*":"Recipe"},"Notes":{"*":"the instructions / recipe / checklist to get things done"},"ValidationRegExJavaScript":{"*":""}},"Boolean":{"Disabled":{"*":false},"Required":{"*":false},"VisibleInEditUI":{"*":true}}}},{"Id":46134,"Version":1,"Guid":"6936443b-32b8-4aff-8e34-c9143f423873","Type":{"Name":"@String","Id":"@String"},"Attributes":{"String":{"DropdownValues":{"*":""},"InputType":{"*":""},"ValidationAutomatic":{"*":""},"ValidationRegEx":{"*":""},"ValidationRegExJavaScript":{"*":""}},"Number":{"RowCount":{"*":1.0}}},"Owner":"dnn:userid=1"}]},{"Name":"Copyright","Type":"String","IsTitle":false,"Metadata":[{"Id":46107,"Version":2,"Guid":"180867b0-dcbe-4e2c-b718-4e1c1df97e26","Type":{"Name":"@All","Id":"@All"},"Attributes":{"String":{"CustomJavaScript":{"*":""},"DefaultValue":{"*":"cc0"},"InputType":{"*":"string-dropdown"},"Name":{"*":"Copyright"},"Notes":{"*":"recipe copyright - important for people who would like to create recipes based on this one"},"ValidationRegExJavaScript":{"*":""}},"Boolean":{"Disabled":{"*":false},"Required":{"*":false},"VisibleInEditUI":{"*":true}}}},{"Id":46108,"Version":2,"Guid":"1ec3684b-33b1-45b7-a381-27ae081b3c7d","Type":{"Name":"@String","Id":"@String"},"Attributes":{"String":{"DropdownValues":{"*":""},"InputType":{"*":""},"ValidationAutomatic":{"*":""},"ValidationRegEx":{"*":""},"ValidationRegExJavaScript":{"*":""}},"Number":{"RowCount":{"*":1.0}}},"Owner":"dnn:userid=1"},{"Id":46109,"Version":2,"Guid":"a682a234-4be0-4301-bdea-184aa4df2848","Type":{"Name":"@string-dropdown","Id":"@string-dropdown"},"Attributes":{"String":{"DropdownValues":{"*":"Public Domain:cc0\nCreative Commons (CC) Attribution:cc-by\nCC Attrib. + ShareAlike:cc-by-sa\nCC Attrib. + Noncommercial:cc-by-nc\nCC Attrib. + Nonderivatives:cc-by-nd\nCC Attrib. + Noncom. + ShareAl.:cc-by-nc-sa\nCC Attrib. + Noncom. + Nonder.:cc-by-nd\nCopyrighted Content:copy"}},"Boolean":{"EnableTextEntry":{"*":true}}}}]}],"Metadata":[]}}