{"_":{"V":1},"Entity":{"Id":42938,"Version":4,"Guid":"95041b6d-8669-4941-a516-47725acfe6ec","Type":{"Name":"DataPipeline","Id":"DataPipeline"},"Attributes":{"String":{"Description":{"*":"Get all attributes of a content-type"},"Name":{"*":"Eav.Queries.Global.Attributes"},"StreamsOut":{"*":"ListContent,Default"},"StreamWiring":{"*":"018a942b-1bad-4124-978c-0d0c35633be1:Default>Out:Default"},"TestParameters":{"*":"[Module:ModuleID]=6936"}},"Boolean":{"AllowEdit":{"*":true}}},"Owner":"dnn:userid=1","Metadata":[{"Id":42980,"Version":2,"Guid":"018a942b-1bad-4124-978c-0d0c35633be1","Type":{"Name":"DataPipelinePart","Id":"DataPipelinePart"},"Attributes":{"String":{"Description":{"*":""},"Name":{"*":"Attributes"},"PartAssemblyAndType":{"*":"ToSic.Eav.DataSources.System.Attributes, ToSic.Eav.DataSources"},"VisualDesignerData":{"*":"{\r\n  \"Top\": 354,\r\n  \"Left\": 400\r\n}"}}},"Owner":"dnn:userid=1","For":{"Target":"Entity","Guid":"95041b6d-8669-4941-a516-47725acfe6ec"}}]}}