{"_":{"V":1},"ContentType":{"Id":"d7858b36-1ef1-4c3d-b15c-c567b0d7bdd4","Name":"MetadataDataSourceConfig","Scope":"System.DataSources","Description":"","Attributes":[{"Name":"Title","Type":"String","InputType":"string-default","IsTitle":true,"Metadata":[{"Id":135532,"Version":2,"Guid":"e44177d1-7756-4a74-aab3-d1a389985e95","Type":{"Name":"@All","Id":"@All"},"Attributes":{"String":{"CustomJavaScript":{"en-us":""},"DefaultValue":{"en-us":"Get Metadata"},"InputType":{"en-us":"string-default"},"Name":{"en-us":"Title"},"Notes":{"en-us":""},"Placeholder":{"en-us":""},"ValidationRegExJavaScript":{"en-us":""}},"Entity":{"Errors":{"*":[]},"Formulas":{"*":[]},"Warnings":{"*":[]}},"Boolean":{"Disabled":{"en-us":false},"DisableTranslation":{"en-us":false},"Required":{"en-us":false},"VisibleInEditUI":{"en-us":true}}},"Owner":"dnn:userid=41"},{"Id":135534,"Version":1,"Guid":"51fd248f-cc49-4659-bcd3-b4ca75662e73","Type":{"Name":"@String","Id":"@String"},"Attributes":{"String":{"DropdownValues":{"en-us":""},"InputType":{"en-us":""}}},"Owner":"dnn:userid=41"},{"Id":135535,"Version":1,"Guid":"6f5e3858-2cae-4dfe-a14d-e18d8e012900","Type":{"Name":"@string-default","Id":"@string-default"},"Attributes":{"String":{"InputFontFamily":{"en-us":""}},"Number":{"RowCount":{"en-us":1.0}}},"Owner":"dnn:userid=41"}]},{"Name":"GroupContentType","Type":"Empty","InputType":"empty-message","IsTitle":false,"Metadata":[{"Id":135538,"Version":4,"Guid":"dfa17e38-9ad9-4587-a6f8-36247aaa96de","Type":{"Name":"@All","Id":"@All"},"Attributes":{"String":{"CustomJavaScript":{"en-us":""},"DefaultValue":{"en-us":""},"InputType":{"*":"empty-message"},"Name":{"en-us":"Advanced (Content-Type)"},"Notes":{"en-us":"<p>In most cases you will just want to get all the metadata of an item, no matter what type the metadata has. But in very complex situation an item could have a lot of metadata, so you may only want to retrieve specific types you care about.&nbsp;</p>"},"Placeholder":{"en-us":""},"ValidationRegExJavaScript":{"en-us":""}},"Entity":{"Errors":{"*":[]},"Formulas":{"*":[]},"Warnings":{"*":[]}},"Boolean":{"Disabled":{"en-us":false},"DisableTranslation":{"en-us":false},"Required":{"en-us":false},"VisibleInEditUI":{"en-us":true}}},"Owner":"dnn:userid=41"},{"Id":135539,"Version":2,"Guid":"6b39e6b4-ab79-4fa1-87fe-43143d73757e","Type":{"Name":"@empty-default","Id":"@empty-default"},"Attributes":{"Boolean":{"DefaultCollapsed":{"en-us":true}}},"Owner":"dnn:userid=41"}]},{"Name":"ContentTypeName","Type":"String","InputType":"string-dropdown-query","IsTitle":false,"Metadata":[{"Id":135533,"Version":3,"Guid":"389f5c99-c5cd-4659-8775-2f853b1a4cfb","Type":{"Name":"@All","Id":"@All"},"Attributes":{"String":{"CustomJavaScript":{"en-us":""},"DefaultValue":{"en-us":""},"InputType":{"en-us":"string-dropdown-query"},"Name":{"en-us":"Content Type Name"},"Notes":{"en-us":""},"Placeholder":{"en-us":""},"ValidationRegExJavaScript":{"en-us":""}},"Entity":{"Errors":{"*":[]},"Formulas":{"*":[]},"Warnings":{"*":[]}},"Boolean":{"Disabled":{"en-us":false},"DisableTranslation":{"en-us":false},"Required":{"en-us":false},"VisibleInEditUI":{"en-us":true}}},"Owner":"dnn:userid=41"},{"Id":135536,"Version":2,"Guid":"53efabfe-b718-422f-8e92-4d9ef480289d","Type":{"Name":"@String","Id":"@String"},"Attributes":{"String":{"DropdownValues":{"en-us":""},"InputType":{"en-us":""}}},"Owner":"dnn:userid=41"},{"Id":135537,"Version":2,"Guid":"3561aa76-6924-4aa1-b892-9dacafbc8628","Type":{"Name":"@string-dropdown-query","Id":"@string-dropdown-query"},"Attributes":{"String":{"Label":{"en-us":"Name"},"Query":{"en-us":"Eav.Queries.Global.ContentTypes"},"Separator":{"en-us":","},"StreamName":{"en-us":"Default"},"UrlParameters":{"en-us":""},"Value":{"en-us":"StaticName"}},"Boolean":{"AllowMultiValue":{"en-us":false},"EnableEdit":{"en-us":false},"EnableRemove":{"en-us":true},"EnableTextEntry":{"en-us":false}}},"Owner":"dnn:userid=41"}]}],"Metadata":[{"Id":135531,"Version":5,"Guid":"b914fbaf-fcbb-412e-8ba2-d2d945274fd2","Type":{"Name":"ContentType","Id":"ContentType"},"Attributes":{"String":{"Description":{"en-us":""},"DynamicChildrenField":{"en-us":""},"EditInstructions":{"en-us":"<p>This will retrieve Metadata of the items in the default stream. In most cases you don't really want to configure much here. See <a href=\"https://r.2sxc.org/DsMetadata\" target=\"_blank\" rel=\"noopener\">Metadata docs</a>.</p>"},"Label":{"en-us":"Metadata DataSource Configuration"},"ListInstructions":{"en-us":""},"Notes":{"en-us":""}},"Hyperlink":{"Icon":{"en-us":""},"Link":{"en-us":"https://r.2sxc.org/DsMetadata"}}},"Owner":"dnn:userid=41","For":{"Target":"ContentType","String":"d7858b36-1ef1-4c3d-b15c-c567b0d7bdd4"}},{"Id":137435,"Version":1,"Guid":"a22bb631-4c0d-4232-b8ca-0f32990aea54","Type":{"Name":"LanguagesDecorator","Id":"e2f569c9-d1dd-4458-a54e-4aaf53e9ae3c"},"Attributes":{"String":{"Title":{"en-us":"Disable Translation"}},"Boolean":{"Enabled":{"en-us":false}}},"Owner":"dnn:userid=41","For":{"Target":"ContentType","String":"d7858b36-1ef1-4c3d-b15c-c567b0d7bdd4"}}]},"Entities":[]}